trell/APIHelper.py
trell/Alerter.py
trell/BigQuery.py
trell/ClickHouse.py
trell/GCSIOHandler.py
trell/MongoDB.py
trell/MySQL.py
trell/S3.py
trell/Uservector.py
trell/__init__.py
trell/aws.py
trell/config.py
trell/exceptions.py
trell/profiler.py
trell/utils.py
trell_ai_util/APIHelper.py
trell_ai_util/BigQueryAdapter.py
trell_ai_util/MysqlAdapter.py
trell_ai_util/S3Adapter.py
trell_ai_util/__init__.py
trell_ai_util/aws.py
trell_ai_util/constants.py
trell_ai_util/profiler.py
trell_ai_util/utils.py
trell_ai_utils-2.3.2.dist-info/METADATA
trell_ai_utils-2.3.2.dist-info/WHEEL
trell_ai_utils-2.3.2.dist-info/top_level.txt
trell_ai_utils-2.3.2.dist-info/RECORD
