Metadata-Version: 2.1
Name: trell-ai-utils
Version: 2.3.2
Summary: Trell Database connectors, slack alerter and loggers
Home-page: https://gitlab.com/trell/trell-ai-util
Author: Abhay Kumar
Author-email: abhay@trell.in
License: UNKNOWN
Platform: UNKNOWN
Classifier: Development Status :: 2 - Pre-Alpha
Classifier: Programming Language :: Python :: 3.8
Classifier: Topic :: Scientific/Engineering :: Artificial Intelligence
Requires-Python: >=3.6.9
Requires-Dist: SQLAlchemy
Requires-Dist: SQLAlchemy-JSONField
Requires-Dist: SQLAlchemy-Utils
Requires-Dist: boto
Requires-Dist: boto3
Requires-Dist: clickhouse-cityhash (==1.0.2.3)
Requires-Dist: clickhouse-driver (==0.1.2)
Requires-Dist: clickhouse-sqlalchemy (==0.1.2)
Requires-Dist: emoji
Requires-Dist: google-cloud
Requires-Dist: google-cloud-bigquery (==2.1.0)
Requires-Dist: google-cloud-datastore (==1.15.0)
Requires-Dist: google-cloud-storage (==1.44.0)
Requires-Dist: joblib
Requires-Dist: json-utils
Requires-Dist: mysql-connector
Requires-Dist: mysql-replication
Requires-Dist: pandas-gbq
Requires-Dist: psutil
Requires-Dist: pymongo (==3.10.0)
Requires-Dist: python-dotenv
Requires-Dist: requests
Requires-Dist: subprocess32
Requires-Dist: tqdm (==4.49.0)
